jupyter_cell/__init__.py
jupyter_cell/__main__.py
jupyter_cell/cli.py
jupyter_cell-2024.9.15.dist-info/LICENSE
jupyter_cell-2024.9.15.dist-info/METADATA
jupyter_cell-2024.9.15.dist-info/WHEEL
jupyter_cell-2024.9.15.dist-info/entry_points.txt
jupyter_cell-2024.9.15.dist-info/top_level.txt
jupyter_cell-2024.9.15.dist-info/RECORD
