Metadata-Version: 2.1
Name: jupyter-cell
Version: 2024.9.15
Summary: Jupyter Notebook → reStructuredText Cells
Author-email: Akshay Mestry <xa@mes3.dev>
License: MIT License
Project-URL: Code, https://github.com/xames3/jupyter-cell
Project-URL: Download, https://pypi.org/project/jupyter-cell/
Project-URL: Homepage, https://github.com/xames3/jupyter-cell/
Project-URL: Issue tracker, https://github.com/xames3/jupyter-cell/issues
Keywords: jupyter,sphinx,python,notebook
Classifier: Development Status :: 5 - Production/Stable
Classifier: Framework :: Sphinx :: Theme
Classifier: Intended Audience :: Developers
Classifier: License :: OSI Approved :: MIT License
Classifier: Operating System :: OS Independent
Classifier: Programming Language :: Python
Classifier: Programming Language :: Python :: 3.11
Classifier: Programming Language :: Python :: 3.12
Classifier: Programming Language :: Python :: 3.13
Classifier: Topic :: Documentation
Classifier: Topic :: Software Development :: Documentation
Requires-Python: >=3.11
License-File: LICENSE
Requires-Dist: notebook
